CHANGELOG.md
ys_dl/__init__.py
ys_dl/apis.py
ys_dl/cli.py
ys_dl/core.py
ys_dl/gui.py
ys_dl-0.1.2.dist-info/entry_points.txt
ys_dl-0.1.2.dist-info/LICENSE
ys_dl-0.1.2.dist-info/WHEEL
ys_dl-0.1.2.dist-info/METADATA
ys_dl-0.1.2.dist-info/RECORD
