Metadata-Version: 2.1
Name: ys-dl
Version: 0.1.2
Summary: Command-line program to download images from Genshin Impact Community
Home-page: https://github.com/XavierJiezou/ys-dl
License: MIT
Keywords: landsat8,cloud,mask
Author: XavierJiezou
Author-email: 878972272@qq.com
Requires-Python: >=3.7,<4.0
Classifier: License :: OSI Approved :: MIT License
Classifier: Programming Language :: Python :: 3
Classifier: Programming Language :: Python :: 3.10
Classifier: Programming Language :: Python :: 3.7
Classifier: Programming Language :: Python :: 3.8
Classifier: Programming Language :: Python :: 3.9
Classifier: Topic :: Software Development :: Libraries :: Python Modules
Requires-Dist: fake-useragent (>=0.1.11,<0.2.0)
Requires-Dist: fire (>=0.4.0,<0.5.0)
Requires-Dist: pyautogui (>=0.9.53,<0.10.0)
Requires-Dist: pyperclip (>=1.8.2,<2.0.0)
Requires-Dist: requests (>=2.27.1,<3.0.0)
Requires-Dist: rich (>=12.3.0,<13.0.0)
Requires-Dist: selenium (>=4.1.5,<5.0.0)
Project-URL: Documentation, https://github.com/XavierJiezou/ys-dl
Project-URL: Repository, https://github.com/XavierJiezou/ys-dl
